BCD.v
module BCD(
    input [3:0] bcd_in,
    output reg [0:6] bcd_out //Cuando se usa la sentencia always se debe usar "reg" en el output 
);

always @(*)
begin 
    case (bcd_in)
        4'b0000: bcd_out= 7'b 1111110; //puede también escribirse como 0: bcd_out= 7'h7E;
        4'b0001: bcd_out= 7'b 0110000;
        4'b0010: bcd_out= 7'b 1101101;
        4'b0011: bcd_out= 7'b 1111001;
        4'b0100: bcd_out= 7'b 0110011;
        4'b0101: bcd_out= 7'b 1011011;
        4'b0110: bcd_out= 7'b 1011111;
        4'b0111: bcd_out= 7'b 1110000;
        4'b1000: bcd_out= 7'b 1111111;
        4'b1001: bcd_out= 7'b 1111011;
        //Los casos después del 10, se pondrán en un default porque para nosotros son don't cares
        default: bcd_out=7'b0000000;
    endcase 
end

endmodule

Practica2/BCD_4displays.v
module BCD_4displays #(parameter N_in=10, N_out=7)(
    input [N_in - 1:0] bcd_in,
    output [N_out-1:0] D_un, D_de, D_ce, D_mi
);

wire [3:0] unidades, decenas, centenas, millares;

assign unidades= bcd_in %10; 
assign decenas= (bcd_in/10)%10;
assign centenas= ((bcd_in/100)%10);
assign millares= (bcd_in/1000);

BCD u(
    .bcd_in(unidades),
    .bcd_out(D_un)
);

BCD d(
    .bcd_in(decenas),
    .bcd_out(D_de)
);

BCD c(
    .bcd_in(centenas),
    .bcd_out(D_ce)
);

BCD m(
    .bcd_in(millares),
    .bcd_out(D_mi)
);

endmodule

Practica2/BCD_4displays_tb.v
module BCD_4displays_tb #(parameter N_in=10, N_out=7)();
    reg [N_in-1:0] bcd_in;
    wire [N_out-1:0] D_u, D_d, D_c, D_m;

    BCD_4displays DUT(
        .bcd_in(bcd_in),
        .D_un(D_u),
        .D_de(D_d),
        .D_ce(D_c),
        .D_mi(D_m)
    );
    
    initial 
        begin
            repeat (1024)
            begin
                bcd_in= $random % 1023;
                #10; 
            end 
            $stop;
            $finish;
        end 

    initial 
        begin 
        $monitor("bcd_in=%b, D_u=%b, D_d=%b, D_c=%b, D_m=%b", bcd_in, D_u, D_d, D_c, D_m);
        end 
    
    initial 
        begin 
            $dumpfile("BCD4Displays.vcd");
            $dumpvars(0, BCD_4displays_tb);
        end

endmodule

BCD4Displays.vcd
$date
	Wed Feb 18 08:01:42 2026
$end
$version
	Icarus Verilog
$end
$timescale
	1s
$end
$scope module BCD_4displays_tb $end
$var wire 7 ! D_u [6:0] $end
$var wire 7 " D_m [6:0] $end
$var wire 7 # D_d [6:0] $end
$var wire 7 $ D_c [6:0] $end
$var parameter 32 % N_in $end
$var parameter 32 & N_out $end
$var reg 10 ' bcd_in [9:0] $end
$scope module DUT $end
$var wire 10 ( bcd_in [9:0] $end
$var wire 4 ) unidades [3:0] $end
$var wire 4 * millares [3:0] $end
$var wire 4 + decenas [3:0] $end
$var wire 4 , centenas [3:0] $end
$var wire 7 - D_un [6:0] $end
$var wire 7 . D_mi [6:0] $end
$var wire 7 / D_de [6:0] $end
$var wire 7 0 D_ce [6:0] $end
$var parameter 32 1 N_in $end
$var parameter 32 2 N_out $end
$scope module c $end
$var wire 4 3 bcd_in [3:0] $end
$var reg 7 4 bcd_out [0:6] $end
$upscope $end
$scope module d $end
$var wire 4 5 bcd_in [3:0] $end
$var reg 7 6 bcd_out [0:6] $end
$upscope $end
$scope module m $end
$var wire 4 7 bcd_in [3:0] $end
$var reg 7 8 bcd_out [0:6] $end
$upscope $end
$scope module u $end
$var wire 4 9 bcd_in [3:0] $end
$var reg 7 : bcd_out [0:6] $end
$upscope $end
$upscope $end
$upscope $end
$enddefinitions $end
$comment Show the parameter values. $end
$dumpall
b111 2
b1010 1
b111 &
b1010 %
$end
#0
$dumpvars
b110011 :
b100 9
b1111110 8
b0 7
b110000 6
b1 5
b1111011 4
b1001 3
b1111011 0
b110000 /
b1111110 .
b110011 -
b1001 ,
b1 +
b0 *
b100 )
b1110010010 (
b1110010010 '
b1111011 $
b110000 #
b1111110 "
b110011 !
$end
#10
b1011011 !
b1011011 -
b1011011 :
b1101101 #
b1101101 /
b1101101 6
b1101101 $
b1101101 0
b1101101 4
b101 )
b101 9
b10 +
b10 5
b10 ,
b10 3
b11100001 '
b11100001 (
#20
b110000 !
b110000 -
b110000 :
b1111110 #
b1111110 /
b1111110 6
b1111011 $
b1111011 0
b1111011 4
b1 )
b1 9
b0 +
b0 5
b1001 ,
b1001 3
b1110000101 '
b1110000101 (
#30
b1110000 !
b1110000 -
b1110000 :
b110011 $
b110011 0
b110011 4
b111 )
b111 9
b100 ,
b100 3
b110010111 '
b110010111 (
#40
b110000 !
b110000 -
b110000 :
b1110000 #
b1110000 /
b1110000 6
b1 )
b1 9
b111 +
b111 5
b111010111 '
b111010111 (
#50
b1101101 !
b1101101 -
b1101101 :
b1111111 #
b1111111 /
b1111111 6
b10 )
b10 9
b1000 +
b1000 5
b111100010 '
b111100010 (
#60
b1111110 !
b1111110 -
b1111110 :
b1011011 #
b1011011 /
b1011011 6
b1111110 $
b1111110 0
b1111110 4
b0 )
b0 9
b101 +
b101 5
b0 ,
b0 3
b110010 '
b110010 (
#70
b110000 !
b110000 -
b110000 :
b1101101 #
b1101101 /
b1101101 6
b110000 $
b110000 0
b110000 4
b1 )
b1 9
b10 +
b10 5
b1 ,
b1 3
b1111001 '
b1111001 (
#80
b1111011 !
b1111011 -
b1111011 :
b1111110 #
b1111110 /
b1111110 6
b1111110 $
b1111110 0
b1111110 4
b1001 )
b1001 9
b0 +
b0 5
b0 ,
b0 3
b1001 '
b1001 (
#90
b1110000 !
b1110000 -
b1110000 :
b1110000 #
b1110000 /
b1110000 6
b1111111 $
b1111111 0
b1111111 4
b111 )
b111 9
b111 +
b111 5
b1000 ,
b1000 3
b1101101101 '
b1101101101 (
#100
b1111011 !
b1111011 -
b1111011 :
b110011 #
b110011 /
b110011 6
b1011011 $
b1011011 0
b1011011 4
b1001 )
b1001 9
b100 +
b100 5
b101 ,
b101 3
b1000100101 '
b1000100101 (
#110
b1011011 !
b1011011 -
b1011011 :
b1011111 #
b1011111 /
b1011111 6
b1011111 $
b1011111 0
b1011111 4
b101 )
b101 9
b110 +
b110 5
b110 ,
b110 3
b1010011001 '
b1010011001 (
#120
b110011 !
b110011 -
b110011 :
b110000 #
b110000 /
b110000 6
b110000 $
b110000 0
b110000 4
b100 )
b100 9
b1 +
b1 5
b1 ,
b1 3
b1110010 '
b1110010 (
#130
b1110000 !
b1110000 -
b1110000 :
b1110000 #
b1110000 /
b1110000 6
b1111111 $
b1111111 0
b1111111 4
b111 )
b111 9
b111 +
b111 5
b1000 ,
b1000 3
b1101101101 '
b1101101101 (
#140
b1011011 !
b1011011 -
b1011011 :
b1101101 #
b1101101 /
b1101101 6
b1111001 $
b1111001 0
b1111001 4
b101 )
b101 9
b10 +
b10 5
b11 ,
b11 3
b101000101 '
b101000101 (
#150
b1111011 #
b1111011 /
b1111011 6
b110000 $
b110000 0
b110000 4
b1001 +
b1001 5
b1 ,
b1 3
b11000011 '
b11000011 (
#160
b110011 !
b110011 -
b110011 :
b110000 #
b110000 /
b110000 6
b1101101 $
b1101101 0
b1101101 4
b100 )
b100 9
b1 +
b1 5
b10 ,
b10 3
b11010110 '
b11010110 (
#170
b1111110 !
b1111110 -
b1111110 :
b110011 #
b110011 /
b110011 6
b0 )
b0 9
b100 +
b100 5
b11110000 '
b11110000 (
#180
b1111001 !
b1111001 -
b1111001 :
b1111111 #
b1111111 /
b1111111 6
b1110000 $
b1110000 0
b1110000 4
b11 )
b11 9
b1000 +
b1000 5
b111 ,
b111 3
b1100001111 '
b1100001111 (
#190
b1111110 !
b1111110 -
b1111110 :
b1101101 #
b1101101 /
b1101101 6
b0 )
b0 9
b10 +
b10 5
b1011010000 '
b1011010000 (
#200
b1110000 !
b1110000 -
b1110000 :
b1011011 #
b1011011 /
b1011011 6
b1111111 $
b1111111 0
b1111111 4
b111 )
b111 9
b101 +
b101 5
b1000 ,
b1000 3
b1101011001 '
b1101011001 (
#210
b1111001 #
b1111001 /
b1111001 6
b11 +
b11 5
b1101000101 '
b1101000101 (
#220
b110000 #
b110000 /
b110000 6
b110011 $
b110011 0
b110011 4
b1 +
b1 5
b100 ,
b100 3
b110100001 '
b110100001 (
#230
b110011 #
b110011 /
b110011 6
b1110000 $
b1110000 0
b1110000 4
b100 +
b100 5
b111 ,
b111 3
b1011101011 '
b1011101011 (
#240
b1111001 !
b1111001 -
b1111001 :
b1111111 #
b1111111 /
b1111111 6
b1011011 $
b1011011 0
b1011011 4
b11 )
b11 9
b1000 +
b1000 5
b101 ,
b101 3
b1001000111 '
b1001000111 (
#250
b110000 !
b110000 -
b110000 :
b1111110 #
b1111110 /
b1111110 6
b1111011 $
b1111011 0
b1111011 4
b1 )
b1 9
b0 +
b0 5
b1001 ,
b1001 3
b1110000101 '
b1110000101 (
#260
b1011111 !
b1011111 -
b1011111 :
b1111011 #
b1111011 /
b1111011 6
b1011011 $
b1011011 0
b1011011 4
b110 )
b110 9
b1001 +
b1001 5
b101 ,
b101 3
b1001010100 '
b1001010100 (
#270
b1111110 !
b1111110 -
b1111110 :
b1011111 #
b1011111 /
b1011111 6
b0 )
b0 9
b110 +
b110 5
b1000110000 '
b1000110000 (
#280
b1111011 !
b1111011 -
b1111011 :
b1111110 #
b1111110 /
b1111110 6
b110000 $
b110000 0
b110000 4
b1001 )
b1001 9
b0 +
b0 5
b1 ,
b1 3
b1101101 '
b1101101 (
#290
b1011111 !
b1011111 -
b1011111 :
b1011011 #
b1011011 /
b1011011 6
b1111111 $
b1111111 0
b1111111 4
b110 )
b110 9
b101 +
b101 5
b1000 ,
b1000 3
b1101011000 '
b1101011000 (
#300
b110011 #
b110011 /
b110011 6
b1111001 $
b1111001 0
b1111001 4
b100 +
b100 5
b11 ,
b11 3
b101011010 '
b101011010 (
#310
b1110000 !
b1110000 -
b1110000 :
b1011111 #
b1011111 /
b1011111 6
b1111110 $
b1111110 0
b1111110 4
b111 )
b111 9
b110 +
b110 5
b0 ,
b0 3
b1000011 '
b1000011 (
#320
b1101101 !
b1101101 -
b1101101 :
b1111001 #
b1111001 /
b1111001 6
b1111001 $
b1111001 0
b1111001 4
b10 )
b10 9
b11 +
b11 5
b11 ,
b11 3
b101001100 '
b101001100 (
#330
b110011 !
b110011 -
b110011 :
b110000 #
b110000 /
b110000 6
b1111111 $
b1111111 0
b1111111 4
b100 )
b100 9
b1 +
b1 5
b1000 ,
b1000 3
b1100101110 '
b1100101110 (
#340
b1011111 !
b1011111 -
b1011111 :
b1110000 #
b1110000 /
b1110000 6
b1101101 $
b1101101 0
b1101101 4
b110 )
b110 9
b111 +
b111 5
b10 ,
b10 3
b100010100 '
b100010100 (
#350
b1111011 !
b1111011 -
b1111011 :
b1111111 #
b1111111 /
b1111111 6
b110000 $
b110000 0
b110000 4
b1001 )
b1001 9
b1000 +
b1000 5
b1 ,
b1 3
b10111101 '
b10111101 (
#360
b1011011 !
b1011011 -
b1011011 :
b1011011 #
b1011011 /
b1011011 6
b1111111 $
b1111111 0
b1111111 4
b101 )
b101 9
b101 +
b101 5
b1000 ,
b1000 3
b1101010111 '
b1101010111 (
#370
b1111111 !
b1111111 -
b1111111 :
b1111110 #
b1111110 /
b1111110 6
b110011 $
b110011 0
b110011 4
b1000 )
b1000 9
b0 +
b0 5
b100 ,
b100 3
b110011000 '
b110011000 (
#380
b110000 !
b110000 -
b110000 :
b1111011 $
b1111011 0
b1111011 4
b1 )
b1 9
b1001 ,
b1001 3
b1110000101 '
b1110000101 (
#390
b1111111 !
b1111111 -
b1111111 :
b1111001 #
b1111001 /
b1111001 6
b1110000 $
b1110000 0
b1110000 4
b1000 )
b1000 9
b11 +
b11 5
b111 ,
b111 3
b1011100010 '
b1011100010 (
#400
b1111011 !
b1111011 -
b1111011 :
b1111111 #
b1111111 /
b1111111 6
b110000 $
b110000 0
b110000 4
b1001 )
b1001 9
b1000 +
b1000 5
b1 ,
b1 3
b10111101 '
b10111101 (
#410
b1111111 !
b1111111 -
b1111111 :
b1110000 #
b1110000 /
b1110000 6
b1110000 $
b1110000 0
b1110000 4
b1000 )
b1000 9
b111 +
b111 5
b111 ,
b111 3
b1100001010 '
b1100001010 (
#420
b1011111 !
b1011111 -
b1011111 :
b1111011 #
b1111011 /
b1111011 6
b1111011 $
b1111011 0
b1111011 4
b110 )
b110 9
b1001 +
b1001 5
b1001 ,
b1001 3
b1111100100 '
b1111100100 (
#430
b1011011 !
b1011011 -
b1011011 :
b1111001 #
b1111001 /
b1111001 6
b110011 $
b110011 0
b110011 4
b101 )
b101 9
b11 +
b11 5
b100 ,
b100 3
b110110011 '
b110110011 (
#440
b1111011 !
b1111011 -
b1111011 :
b110000 #
b110000 /
b110000 6
b1011011 $
b1011011 0
b1011011 4
b1001 )
b1001 9
b1 +
b1 5
b101 ,
b101 3
b1000000111 '
b1000000111 (
#450
b1111110 !
b1111110 -
b1111110 :
b1111111 #
b1111111 /
b1111111 6
b1011111 $
b1011111 0
b1011111 4
b0 )
b0 9
b1000 +
b1000 5
b110 ,
b110 3
b1010101000 '
b1010101000 (
#460
b1011011 !
b1011011 -
b1011011 :
b110011 #
b110011 /
b110011 6
b1111111 $
b1111111 0
b1111111 4
b101 )
b101 9
b100 +
b100 5
b1000 ,
b1000 3
b1101001101 '
b1101001101 (
#470
b1110000 !
b1110000 -
b1110000 :
b1111011 $
b1111011 0
b1111011 4
b111 )
b111 9
b1001 ,
b1001 3
b1110110011 '
b1110110011 (
#480
b110011 !
b110011 -
b110011 :
b1111111 #
b1111111 /
b1111111 6
b110011 $
b110011 0
b110011 4
b100 )
b100 9
b1000 +
b1000 5
b100 ,
b100 3
b111100100 '
b111100100 (
#490
b1011011 !
b1011011 -
b1011011 :
b1101101 #
b1101101 /
b1101101 6
b1011111 $
b1011111 0
b1011111 4
b101 )
b101 9
b10 +
b10 5
b110 ,
b110 3
b1001110001 '
b1001110001 (
#500
b1111001 !
b1111001 -
b1111001 :
b1011011 #
b1011011 /
b1011011 6
b1111011 $
b1111011 0
b1111011 4
b11 )
b11 9
b101 +
b101 5
b1001 ,
b1001 3
b1110111001 '
b1110111001 (
#510
b110011 !
b110011 -
b110011 :
b1110000 #
b1110000 /
b1110000 6
b1111001 $
b1111001 0
b1111001 4
b100 )
b100 9
b111 +
b111 5
b11 ,
b11 3
b101110110 '
b101110110 (
#520
b1111001 #
b1111001 /
b1111001 6
b1011111 $
b1011111 0
b1011111 4
b11 +
b11 5
b110 ,
b110 3
b1001111010 '
b1001111010 (
#530
b1111111 !
b1111111 -
b1111111 :
b110000 #
b110000 /
b110000 6
b1000 )
b1000 9
b1 +
b1 5
b1001101010 '
b1001101010 (
#540
b1110000 !
b1110000 -
b1110000 :
b1111111 #
b1111111 /
b1111111 6
b1111111 $
b1111111 0
b1111111 4
b111 )
b111 9
b1000 +
b1000 5
b1000 ,
b1000 3
b1101110111 '
b1101110111 (
#550
b1101101 !
b1101101 -
b1101101 :
b110011 #
b110011 /
b110011 6
b1111001 $
b1111001 0
b1111001 4
b10 )
b10 9
b100 +
b100 5
b11 ,
b11 3
b101010110 '
b101010110 (
#560
b1011011 #
b1011011 /
b1011011 6
b1011111 $
b1011111 0
b1011111 4
b101 +
b101 5
b110 ,
b110 3
b1010001100 '
b1010001100 (
#570
b110000 !
b110000 -
b110000 :
b1111110 #
b1111110 /
b1111110 6
b1111110 $
b1111110 0
b1111110 4
b1 )
b1 9
b0 +
b0 5
b0 ,
b0 3
b1 '
b1 (
#580
b1101101 !
b1101101 -
b1101101 :
b1011111 #
b1011111 /
b1011111 6
b1110000 $
b1110000 0
b1110000 4
b10 )
b10 9
b110 +
b110 5
b111 ,
b111 3
b1011111010 '
b1011111010 (
#590
b1111001 !
b1111001 -
b1111001 :
b110000 #
b110000 /
b110000 6
b1011111 $
b1011111 0
b1011111 4
b11 )
b11 9
b1 +
b1 5
b110 ,
b110 3
b1001100101 '
b1001100101 (
#600
b110011 !
b110011 -
b110011 :
b1111111 #
b1111111 /
b1111111 6
b110011 $
b110011 0
b110011 4
b100 )
b100 9
b1000 +
b1000 5
b100 ,
b100 3
b111100100 '
b111100100 (
#610
b1011111 !
b1011111 -
b1011111 :
b1101101 #
b1101101 /
b1101101 6
b1011111 $
b1011111 0
b1011111 4
b110 )
b110 9
b10 +
b10 5
b110 ,
b110 3
b1001110010 '
b1001110010 (
#620
b1111111 !
b1111111 -
b1111111 :
b1110000 #
b1110000 /
b1110000 6
b1111110 $
b1111110 0
b1111110 4
b1000 )
b1000 9
b111 +
b111 5
b0 ,
b0 3
b1001110 '
b1001110 (
#630
b110000 !
b110000 -
b110000 :
b1111110 #
b1111110 /
b1111110 6
b110000 "
b110000 .
b110000 8
b1 )
b1 9
b0 +
b0 5
b1 *
b1 7
b1111101001 '
b1111101001 (
#640
b1111111 #
b1111111 /
b1111111 6
b1011011 $
b1011011 0
b1011011 4
b1111110 "
b1111110 .
b1111110 8
b1000 +
b1000 5
b101 ,
b101 3
b0 *
b0 7
b1001000101 '
b1001000101 (
#650
b1111110 !
b1111110 -
b1111110 :
b1111110 #
b1111110 /
b1111110 6
b110000 $
b110000 0
b110000 4
b0 )
b0 9
b0 +
b0 5
b1 ,
b1 3
b1100100 '
b1100100 (
#660
b1111001 !
b1111001 -
b1111001 :
b1111001 $
b1111001 0
b1111001 4
b11 )
b11 9
b11 ,
b11 3
b100101111 '
b100101111 (
#670
b1011111 #
b1011111 /
b1011111 6
b1011111 $
b1011111 0
b1011111 4
b110 +
b110 5
b110 ,
b110 3
b1010010111 '
b1010010111 (
#680
b1111111 !
b1111111 -
b1111111 :
b1101101 #
b1101101 /
b1101101 6
b1111111 $
b1111111 0
b1111111 4
b1000 )
b1000 9
b10 +
b10 5
b1000 ,
b1000 3
b1100111100 '
b1100111100 (
#690
b110011 !
b110011 -
b110011 :
b1111011 #
b1111011 /
b1111011 6
b1011011 $
b1011011 0
b1011011 4
b100 )
b100 9
b1001 +
b1001 5
b101 ,
b101 3
b1001010010 '
b1001010010 (
#700
b1110000 !
b1110000 -
b1110000 :
b1111111 #
b1111111 /
b1111111 6
b110011 $
b110011 0
b110011 4
b111 )
b111 9
b1000 +
b1000 5
b100 ,
b100 3
b111100111 '
b111100111 (
#710
b1111011 !
b1111011 -
b1111011 :
b1111001 #
b1111001 /
b1111001 6
b1001 )
b1001 9
b11 +
b11 5
b110110111 '
b110110111 (
#720
b1101101 !
b1101101 -
b1101101 :
b1101101 #
b1101101 /
b1101101 6
b1111111 $
b1111111 0
b1111111 4
b10 )
b10 9
b10 +
b10 5
b1000 ,
b1000 3
b1100110110 '
b1100110110 (
#730
b110011 !
b110011 -
b110011 :
b110000 #
b110000 /
b110000 6
b100 )
b100 9
b1 +
b1 5
b1100101110 '
b1100101110 (
#740
b110000 !
b110000 -
b110000 :
b1011011 #
b1011011 /
b1011011 6
b1110000 $
b1110000 0
b1110000 4
b1 )
b1 9
b101 +
b101 5
b111 ,
b111 3
b1011101111 '
b1011101111 (
#750
b1011111 !
b1011111 -
b1011111 :
b110000 #
b110000 /
b110000 6
b110000 $
b110000 0
b110000 4
b110 )
b110 9
b1 +
b1 5
b1 ,
b1 3
b1110100 '
b1110100 (
#760
b1111011 !
b1111011 -
b1111011 :
b1111011 #
b1111011 /
b1111011 6
b1101101 $
b1101101 0
b1101101 4
b1001 )
b1001 9
b1001 +
b1001 5
b10 ,
b10 3
b100101011 '
b100101011 (
#770
b1111110 !
b1111110 -
b1111110 :
b1011111 #
b1011111 /
b1011111 6
b110011 $
b110011 0
b110011 4
b0 )
b0 9
b110 +
b110 5
b100 ,
b100 3
b111001100 '
b111001100 (
#780
b1110000 !
b1110000 -
b1110000 :
b1110000 #
b1110000 /
b1110000 6
b110000 $
b110000 0
b110000 4
b111 )
b111 9
b111 +
b111 5
b1 ,
b1 3
b10110001 '
b10110001 (
#790
b1111110 !
b1111110 -
b1111110 :
b1111111 #
b1111111 /
b1111111 6
b1011111 $
b1011111 0
b1011111 4
b0 )
b0 9
b1000 +
b1000 5
b110 ,
b110 3
b1010101000 '
b1010101000 (
#800
b110000 !
b110000 -
b110000 :
b1011011 #
b1011011 /
b1011011 6
b1011011 $
b1011011 0
b1011011 4
b1 )
b1 9
b101 +
b101 5
b101 ,
b101 3
b1000100111 '
b1000100111 (
#810
b1111011 !
b1111011 -
b1111011 :
b1011111 #
b1011111 /
b1011111 6
b1111111 $
b1111111 0
b1111111 4
b1001 )
b1001 9
b110 +
b110 5
b1000 ,
b1000 3
b1101100101 '
b1101100101 (
#820
b1101101 !
b1101101 -
b1101101 :
b1111001 #
b1111001 /
b1111001 6
b1111110 $
b1111110 0
b1111110 4
b10 )
b10 9
b11 +
b11 5
b0 ,
b0 3
b100000 '
b100000 (
#830
b1011111 !
b1011111 -
b1011111 :
b110011 #
b110011 /
b110011 6
b1011011 $
b1011011 0
b1011011 4
b110 )
b110 9
b100 +
b100 5
b101 ,
b101 3
b1000100010 '
b1000100010 (
#840
b1111011 !
b1111011 -
b1111011 :
b1111001 #
b1111001 /
b1111001 6
b1111111 $
b1111111 0
b1111111 4
b1001 )
b1001 9
b11 +
b11 5
b1000 ,
b1000 3
b1101000111 '
b1101000111 (
#850
b1111110 !
b1111110 -
b1111110 :
b1101101 #
b1101101 /
b1101101 6
b1101101 $
b1101101 0
b1101101 4
b0 )
b0 9
b10 +
b10 5
b10 ,
b10 3
b11011100 '
b11011100 (
#860
b1111011 !
b1111011 -
b1111011 :
b110011 #
b110011 /
b110011 6
b110000 $
b110000 0
b110000 4
b1001 )
b1001 9
b100 +
b100 5
b1 ,
b1 3
b10010101 '
b10010101 (
#870
b1110000 !
b1110000 -
b1110000 :
b110000 #
b110000 /
b110000 6
b1110000 $
b1110000 0
b1110000 4
b111 )
b111 9
b1 +
b1 5
b111 ,
b111 3
b1011001101 '
b1011001101 (
#880
b1111011 !
b1111011 -
b1111011 :
b1111110 #
b1111110 /
b1111110 6
b1111110 $
b1111110 0
b1111110 4
b1001 )
b1001 9
b0 +
b0 5
b0 ,
b0 3
b1001 '
b1001 (
#890
b1101101 !
b1101101 -
b1101101 :
b1101101 #
b1101101 /
b1101101 6
b1011011 $
b1011011 0
b1011011 4
b10 )
b10 9
b10 +
b10 5
b101 ,
b101 3
b1000001010 '
b1000001010 (
#900
b1111011 !
b1111011 -
b1111011 :
b1111110 #
b1111110 /
b1111110 6
b1110000 $
b1110000 0
b1110000 4
b1001 )
b1001 9
b0 +
b0 5
b111 ,
b111 3
b1011000101 '
b1011000101 (
#910
b1111011 #
b1111011 /
b1111011 6
b1111011 $
b1111011 0
b1111011 4
b1001 +
b1001 5
b1001 ,
b1001 3
b1111100111 '
b1111100111 (
#920
b1101101 #
b1101101 /
b1101101 6
b1110000 $
b1110000 0
b1110000 4
b10 +
b10 5
b111 ,
b111 3
b1011011001 '
b1011011001 (
#930
b1111110 !
b1111110 -
b1111110 :
b1111001 #
b1111001 /
b1111001 6
b110011 $
b110011 0
b110011 4
b0 )
b0 9
b11 +
b11 5
b100 ,
b100 3
b110101110 '
b110101110 (
#940
b1101101 !
b1101101 -
b1101101 :
b1110000 #
b1110000 /
b1110000 6
b1011011 $
b1011011 0
b1011011 4
b10 )
b10 9
b111 +
b111 5
b101 ,
b101 3
b1000111100 '
b1000111100 (
#950
b1011111 !
b1011111 -
b1011111 :
b1111011 #
b1111011 /
b1111011 6
b1111111 $
b1111111 0
b1111111 4
b110 )
b110 9
b1001 +
b1001 5
b1000 ,
b1000 3
b1110000000 '
b1110000000 (
#960
b1101101 !
b1101101 -
b1101101 :
b110000 $
b110000 0
b110000 4
b10 )
b10 9
b1 ,
b1 3
b11000000 '
b11000000 (
#970
b110000 #
b110000 /
b110000 6
b1 +
b1 5
b1110000 '
b1110000 (
#980
b110000 !
b110000 -
b110000 :
b1011011 $
b1011011 0
b1011011 4
b1 )
b1 9
b101 ,
b101 3
b111111111 '
b111111111 (
#990
b1110000 !
b1110000 -
b1110000 :
b110011 #
b110011 /
b110011 6
b1111001 $
b1111001 0
b1111001 4
b111 )
b111 9
b100 +
b100 5
b11 ,
b11 3
b101011011 '
b101011011 (
#1000
b1111011 !
b1111011 -
b1111011 :
b110000 #
b110000 /
b110000 6
b1110000 $
b1110000 0
b1110000 4
b1001 )
b1001 9
b1 +
b1 5
b111 ,
b111 3
b1011001111 '
b1011001111 (
#1010
b110000 !
b110000 -
b110000 :
b1111110 #
b1111110 /
b1111110 6
b110000 $
b110000 0
b110000 4
b1 )
b1 9
b0 +
b0 5
b1 ,
b1 3
b1100101 '
b1100101 (
#1020
b1111001 !
b1111001 -
b1111001 :
b1111001 #
b1111001 /
b1111001 6
b1101101 $
b1101101 0
b1101101 4
b11 )
b11 9
b11 +
b11 5
b10 ,
b10 3
b11101001 '
b11101001 (
#1030
b110011 !
b110011 -
b110011 :
b1111011 $
b1111011 0
b1111011 4
b100 )
b100 9
b1001 ,
b1001 3
b1110100110 '
b1110100110 (
#1040
b1101101 !
b1101101 -
b1101101 :
b1111111 #
b1111111 /
b1111111 6
b1111111 $
b1111111 0
b1111111 4
b10 )
b10 9
b1000 +
b1000 5
b1000 ,
b1000 3
b1101110010 '
b1101110010 (
#1050
b1011111 !
b1011111 -
b1011111 :
b1111001 #
b1111001 /
b1111001 6
b110000 $
b110000 0
b110000 4
b110 )
b110 9
b11 +
b11 5
b1 ,
b1 3
b10001000 '
b10001000 (
#1060
b1111111 !
b1111111 -
b1111111 :
b1111011 #
b1111011 /
b1111011 6
b1111111 $
b1111111 0
b1111111 4
b1000 )
b1000 9
b1001 +
b1001 5
b1000 ,
b1000 3
b1110000010 '
b1110000010 (
#1070
b110000 !
b110000 -
b110000 :
b1 )
b1 9
b1101111011 '
b1101111011 (
#1080
b1101101 #
b1101101 /
b1101101 6
b10 +
b10 5
b1100110101 '
b1100110101 (
#1090
b110011 !
b110011 -
b110011 :
b1111110 #
b1111110 /
b1111110 6
b1101101 $
b1101101 0
b1101101 4
b100 )
b100 9
b0 +
b0 5
b10 ,
b10 3
b11001100 '
b11001100 (
#1100
b1110000 !
b1110000 -
b1110000 :
b110011 #
b110011 /
b110011 6
b110000 $
b110000 0
b110000 4
b111 )
b111 9
b100 +
b100 5
b1 ,
b1 3
b10010011 '
b10010011 (
#1110
b1111011 !
b1111011 -
b1111011 :
b1011111 #
b1011111 /
b1011111 6
b1001 )
b1001 9
b110 +
b110 5
b10101001 '
b10101001 (
#1120
b1111111 !
b1111111 -
b1111111 :
b110000 #
b110000 /
b110000 6
b1111110 $
b1111110 0
b1111110 4
b1000 )
b1000 9
b1 +
b1 5
b0 ,
b0 3
b10010 '
b10010 (
#1130
b1011011 !
b1011011 -
b1011011 :
b110011 #
b110011 /
b110011 6
b1101101 $
b1101101 0
b1101101 4
b101 )
b101 9
b100 +
b100 5
b10 ,
b10 3
b11110101 '
b11110101 (
#1140
b110000 !
b110000 -
b110000 :
b1111111 #
b1111111 /
b1111111 6
b1111111 $
b1111111 0
b1111111 4
b1 )
b1 9
b1000 +
b1000 5
b1000 ,
b1000 3
b1101110001 '
b1101110001 (
#1150
b1011111 !
b1011111 -
b1011111 :
b1101101 #
b1101101 /
b1101101 6
b110011 $
b110011 0
b110011 4
b110 )
b110 9
b10 +
b10 5
b100 ,
b100 3
b110101010 '
b110101010 (
#1160
b1011011 !
b1011011 -
b1011011 :
b110000 #
b110000 /
b110000 6
b1111110 $
b1111110 0
b1111110 4
b110000 "
b110000 .
b110000 8
b101 )
b101 9
b1 +
b1 5
b0 ,
b0 3
b1 *
b1 7
b1111110111 '
b1111110111 (
#1170
b1111110 !
b1111110 -
b1111110 :
b0 )
b0 9
b1111110010 '
b1111110010 (
#1180
b110011 !
b110011 -
b110011 :
b1111011 #
b1111011 /
b1111011 6
b1111110 "
b1111110 .
b1111110 8
b100 )
b100 9
b1001 +
b1001 5
b0 *
b0 7
b1011110 '
b1011110 (
#1190
b1111110 !
b1111110 -
b1111110 :
b1111110 #
b1111110 /
b1111110 6
b110000 $
b110000 0
b110000 4
b0 )
b0 9
b0 +
b0 5
b1 ,
b1 3
b1100100 '
b1100100 (
#1200
b110011 !
b110011 -
b110011 :
b110000 #
b110000 /
b110000 6
b1011111 $
b1011111 0
b1011111 4
b100 )
b100 9
b1 +
b1 5
b110 ,
b110 3
b1001100110 '
b1001100110 (
#1210
b1101101 !
b1101101 -
b1101101 :
b1111111 #
b1111111 /
b1111111 6
b1110000 $
b1110000 0
b1110000 4
b10 )
b10 9
b1000 +
b1000 5
b111 ,
b111 3
b1100001110 '
b1100001110 (
#1220
b1111011 !
b1111011 -
b1111011 :
b1111001 #
b1111001 /
b1111001 6
b110000 $
b110000 0
b110000 4
b1001 )
b1001 9
b11 +
b11 5
b1 ,
b1 3
b10001011 '
b10001011 (
#1230
b1111110 !
b1111110 -
b1111110 :
b1111111 #
b1111111 /
b1111111 6
b1111001 $
b1111001 0
b1111001 4
b0 )
b0 9
b1000 +
b1000 5
b11 ,
b11 3
b101111100 '
b101111100 (
#1240
b1111011 #
b1111011 /
b1111011 6
b1110000 $
b1110000 0
b1110000 4
b1001 +
b1001 5
b111 ,
b111 3
b1100010110 '
b1100010110 (
#1250
b1011111 !
b1011111 -
b1011111 :
b1111111 $
b1111111 0
b1111111 4
b110 )
b110 9
b1000 ,
b1000 3
b1110000000 '
b1110000000 (
#1260
b1111011 !
b1111011 -
b1111011 :
b1111001 $
b1111001 0
b1111001 4
b1001 )
b1001 9
b11 ,
b11 3
b110001111 '
b110001111 (
#1270
b1110000 !
b1110000 -
b1110000 :
b1111111 #
b1111111 /
b1111111 6
b110011 $
b110011 0
b110011 4
b111 )
b111 9
b1000 +
b1000 5
b100 ,
b100 3
b111100111 '
b111100111 (
